request_id/__init__.py
request_id/middleware.py
request_id_flask-0.0.4.dist-info/LICENSE
request_id_flask-0.0.4.dist-info/METADATA
request_id_flask-0.0.4.dist-info/WHEEL
request_id_flask-0.0.4.dist-info/top_level.txt
request_id_flask-0.0.4.dist-info/RECORD
