Metadata-Version: 2.1
Name: request-id-flask
Version: 0.0.4
Summary: Receive and return the value of HTTP X-Request-ID header.
Home-page: https://github.com/fili/request-id-flask
Author: Fili
Author-email: dev@fili.com
License: MIT
Classifier: Programming Language :: Python :: 3
Classifier: Programming Language :: Python :: 3.6
Classifier: Programming Language :: Python :: 3.7
Classifier: Programming Language :: Python :: 3.8
Classifier: Programming Language :: Python :: 3.9
Classifier: Programming Language :: Python :: 3.10
Classifier: Programming Language :: Python :: 3.11
Classifier: Programming Language :: Python :: 3.12
Classifier: Operating System :: OS Independent
Classifier: License :: OSI Approved :: MIT License
Requires-Python: >=3.6
License-File: LICENSE
Requires-Dist: flask
Requires-Dist: uuid
Requires-Dist: quart
